easylab/__init__.py
easylab/easylab.py
easylab-2.4.dist-info/WHEEL
easylab-2.4.dist-info/METADATA
easylab-2.4.dist-info/RECORD
