Metadata-Version: 2.1
Name: easylab
Version: 2.4
Summary: Offers simple solutions for challenges that can be encountered in the psychology labs.
Home-page: https://github.com/altunenes/EasyLab
License: MIT
Keywords: GUI, psychology,experimental-psychology,e-prime,spatial-frequency,altunenes
Author: altunenes
Author-email: enesaltun2@gmail.com
Requires-Python: >=3.8,<4.0
Classifier: Intended Audience :: Education
Classifier: Intended Audience :: Science/Research
Classifier: License :: OSI Approved :: MIT License
Classifier: Operating System :: OS Independent
Classifier: Programming Language :: Python :: 3
Classifier: Programming Language :: Python :: 3.8
Classifier: Programming Language :: Python :: 3.9
Classifier: Programming Language :: Python :: 3.10
Classifier: Programming Language :: Python :: 3.11
Classifier: Programming Language :: Python :: 3
Classifier: Programming Language :: Python :: 3.6
Classifier: Programming Language :: Python :: 3.7
Classifier: Programming Language :: Python :: 3.8
Classifier: Topic :: Software Development :: Libraries :: Python Modules
Project-URL: Repository, https://github.com/altunenes/EasyLab
